pymrmr.cpython-37m-darwin.so
pymrmr/crank.cpp
pymrmr/mrmr.cpp
pymrmr/nrutil.cpp
pymrmr/nrutil.h
pymrmr/pbetai.cpp
pymrmr/pymrmr.cpp
pymrmr/pymrmr.pyx
pymrmr/sort2.cpp
pymrmr-0.1.11.dist-info/AUTHORS.rst
pymrmr-0.1.11.dist-info/LICENSE
pymrmr-0.1.11.dist-info/METADATA
pymrmr-0.1.11.dist-info/WHEEL
pymrmr-0.1.11.dist-info/top_level.txt
pymrmr-0.1.11.dist-info/RECORD
