Metadata-Version: 2.1
Name: pymrmr
Version: 0.1.11
Summary: Python3 binding to mRMR Feature Selection algorithm
Home-page: https://github.com/fbrundu/pymrmr
Author: Francesco G. Brundu
Author-email: francesco.brundu@gmail.com
License: MIT license
Keywords: pymrmr
Platform: UNKNOWN
Classifier: Development Status :: 2 - Pre-Alpha
Classifier: Intended Audience :: Developers
Classifier: License :: OSI Approved :: MIT License
Classifier: Natural Language :: English
Classifier: Programming Language :: Python :: 3.6
Requires-Dist: numpy (>=1.19.5)
